pysprint/PySPRINT.py
pysprint/fileio.py
pysprint/data_utils.py
pysprint/prediction_matrix.py
pysprint/pysprint.cpython-39-x86_64-linux-gnu.so
pysprint/pysprint.cpython-38-x86_64-linux-gnu.so
pysprint/__init__.py
pysprintppi-1.1.dist-info/RECORD
pysprintppi-1.1.dist-info/top_level.txt
pysprintppi-1.1.dist-info/METADATA
pysprintppi-1.1.dist-info/WHEEL
pysprintppi-1.1.dist-info/LICENSE
