Metadata-Version: 2.1
Name: pysprintppi
Version: 1.1
Summary: Protein-protein interaction predictor
Home-page: UNKNOWN
Author: Francois Charih
Author-email: francoischarih@sce.carleton.ca
License: UNKNOWN
Platform: UNKNOWN
Requires-Dist: beautifulsoup4
Requires-Dist: biopython
Requires-Dist: neovim
Requires-Dist: numpy
Requires-Dist: requests
Requires-Dist: mpi4py
